eom/__init__.py
eom/auth.py
eom/bastion.py
eom/governor.py
eom/metrics.py
eom/rbac.py
eom/version.py
eom/tests/__init__.py
eom/utils/__init__.py
eom/utils/log.py
eom/utils/redis_pool.py
eom/uwsgi/README.rst
eom/uwsgi/__init__.py
eom/uwsgi/logvar_mapper.py
eom-0.8.2.dist-info/DESCRIPTION.rst
eom-0.8.2.dist-info/METADATA
eom-0.8.2.dist-info/RECORD
eom-0.8.2.dist-info/WHEEL
eom-0.8.2.dist-info/metadata.json
eom-0.8.2.dist-info/pbr.json
eom-0.8.2.dist-info/top_level.txt
